backblaze_uploader/__init__.py
backblaze_uploader/uploader.py
tests/__init__.py
tests/test_uploader.py
backblaze_uploader-0.1.1.dist-info/LICENSE
backblaze_uploader-0.1.1.dist-info/METADATA
backblaze_uploader-0.1.1.dist-info/WHEEL
backblaze_uploader-0.1.1.dist-info/top_level.txt
backblaze_uploader-0.1.1.dist-info/RECORD
