Metadata-Version: 2.1
Name: backblaze-uploader
Version: 0.1.1
Summary: Backblaze B2 bucket'ga fayl yuklash uchun Python library
Home-page: https://github.com/Muhiddin0/backbleaze_uploader
Author: Kumosense
Author-email: kabraliev2005@gmail.com
License: UNKNOWN
Platform: UNKNOWN
Classifier: Programming Language :: Python :: 3
Classifier: License :: OSI Approved :: MIT License
Classifier: Operating System :: OS Independent
Requires-Python: >=3.6
License-File: LICENSE
Requires-Dist: b2sdk>=1.0.0
